<?xml version='1.0' encoding='utf-8'?>
<list>
    <command name="gmshop" path="pages/services-gmshop.htm" />
    <command name="account_service" path="pages/account-service.htm" />
    <command name="auction_house" path="pages/auction-house.htm" />
    <command name="cabinet" path="pages/cabinet.htm" />
    <command name="clan" path="pages/clan.htm" />
    <command name="events" path="pages/events.htm" />
    <command name="home" path="pages/home.htm" />
    <command name="raids" path="pages/raids.htm" />
    <command name="rankings" path="pages/rankings.htm" />
    <command name="services" path="pages/services.htm" />
    <command name="buffer" path="pages/services-buffer.htm" />
    <command name="buffer_createscheme" path="pages/services-buffer-createscheme.htm" />
    <command name="buffer_editscheme" path="pages/services-buffer-editscheme.htm" />
    <command name="classmaster" path="pages/services-classmaster.htm" />
    <command name="donationstore" path="pages/services-donationstore.htm" />
    <command name="gatekeeper" path="pages/services-gatekeeper.htm" />
    <command name="warehouse" path="pages/services-warehouse.htm" />
</list>
